minilineplot.py
minilineplot-0.0.8.dist-info/licenses/LICENSE
minilineplot-0.0.8.dist-info/WHEEL
minilineplot-0.0.8.dist-info/METADATA
minilineplot-0.0.8.dist-info/RECORD
