Metadata-Version: 2.4
Name: minilineplot
Version: 0.0.8
Summary: A single Python module, with no dependencies, producing an SVG image of a chart with one or more plotted lines
Keywords: chart,line,plot,graph
Author-email: Bernard Czenkusz <bernie@skipole.co.uk>
Requires-Python: >=3.10
License-Expression: Unlicense
Classifier: Topic :: Scientific/Engineering
Classifier: Topic :: Office/Business
Classifier: Topic :: Education
License-File: LICENSE
Project-URL: Source, https://github.com/bernie-skipole/minilineplot
